<?xml version="1.0" encoding="utf-8"?>
<VirtualDB xmlns:xsi="http://www.w3.org/2001/XMLSchema-instance" xmlns:xsd="http://www.w3.org/2001/XMLSchema" version="8.2.0">
  <Name>vdb</Name>
  <RootView />
  <RootViewRecordType />
  <LuLazyDataUpdate syncMethod="None" performEvery="1.00:00:00" />
  <EventsList />
  <IidFinderProp enabled="false">
    <NumberOfPartitions>100</NumberOfPartitions>
    <NumberOfJobs>50</NumberOfJobs>
  </IidFinderProp>
  <Tables />
  <TablesProperties />
  <EnrichmentsOrderList />
  <ReferencesList />
  <Relations />
  <DatabaseRelations />
  <PreVCsSqlScript />
  <PostVCsSqlScript />
  <Indexes />
  <LudbProperties />
</VirtualDB>